[
    {
        "title": "The First Communicants",
        "contentId": 244792,
        "artistContentId": 244678,
        "artistName": "Balthus",
        "completitionYear": 1926,
        "yearAsString": "1926",
        "width": 502,
        "image": "https://uploads6.wikiart.org/images/balthus/the-first-communicants-1926.jpg!Large.jpg",
        "height": 512,
        "artistUrl": "balthus",
        "url": "the-first-communicants-1926",
        "dictionaries": [
            417,
            502
        ],
        "location": null,
        "period": null,
        "serie": null,
        "genre": "genre painting",
        "material": null,
        "style": "Expressionism",
        "technique": null,
        "sizeX": null,
        "sizeY": null,
        "diameter": null,
        "auction": null,
        "yearOfTrade": null,
        "lastPrice": null,
        "galleryName": "Tate Modern, London, UK",
        "tags": "allegories-and-symbols",
        "description": null
    },
    {
        "title": "Cathy's toilette",
        "contentId": 244685,
        "artistContentId": 244678,
        "artistName": "Balthus",
        "completitionYear": 1933,
        "yearAsString": "1933",
        "width": 1436,
        "image": "https://uploads0.wikiart.org/images/balthus/cathy-s-toilette-1933.jpg!Large.jpg",
        "height": 1579,
        "artistUrl": "balthus",
        "url": "cathy-s-toilette-1933",
        "dictionaries": [
            417,
            496
        ],
        "location": null,
        "period": null,
        "serie": null,
        "genre": "literary painting",
        "material": null,
        "style": "Expressionism",
        "technique": null,
        "sizeX": null,
        "sizeY": null,
        "diameter": null,
        "auction": null,
        "yearOfTrade": null,
        "lastPrice": null,
        "galleryName": "Georges Pompidou Center, Paris, France",
        "tags": "female-nude, women-and-mirrors",
        "description": null
    },
    {
        "title": "The Barracks",
        "contentId": 244781,
        "artistContentId": 244678,
        "artistName": "Balthus",
        "completitionYear": 1933,
        "yearAsString": "1933",
        "width": 1632,
        "image": "https://uploads5.wikiart.org/images/balthus/the-barracks-1933.jpg!Large.jpg",
        "height": 1311,
        "artistUrl": "balthus",
        "url": "the-barracks-1933",
        "dictionaries": [
            432,
            481,
            502
        ],
        "location": null,
        "period": null,
        "serie": null,
        "genre": "genre painting",
        "material": null,
        "style": "Metaphysical art, Surrealism",
        "technique": null,
        "sizeX": null,
        "sizeY": null,
        "diameter": null,
        "auction": null,
        "yearOfTrade": null,
        "lastPrice": null,
        "galleryName": null,
        "tags": "animals, horses, hunting-and-racing",
        "description": null
    },
    {
        "title": "The Fear of Ghosts",
        "contentId": 244791,
        "artistContentId": 244678,
        "artistName": "Balthus",
        "completitionYear": 1933,
        "yearAsString": "1933",
        "width": 1241,
        "image": "https://uploads2.wikiart.org/images/balthus/the-fear-of-ghosts-1933.jpg!Large.jpg",
        "height": 1765,
        "artistUrl": "balthus",
        "url": "the-fear-of-ghosts-1933",
        "dictionaries": [
            481,
            502
        ],
        "location": null,
        "period": null,
        "serie": null,
        "genre": "genre painting",
        "material": null,
        "style": "Surrealism",
        "technique": null,
        "sizeX": 114.3,
        "sizeY": 162.2,
        "diameter": null,
        "auction": null,
        "yearOfTrade": null,
        "lastPrice": null,
        "galleryName": null,
        "tags": "doors-and-windows, characters-and-emotions",
        "description": null
    },
    {
        "title": "The street",
        "contentId": 244803,
        "artistContentId": 244678,
        "artistName": "Balthus",
        "completitionYear": 1933,
        "yearAsString": "1933",
        "width": 2423,
        "image": "https://uploads3.wikiart.org/images/balthus/the-street-1933.jpg!Large.jpg",
        "height": 1979,
        "artistUrl": "balthus",
        "url": "the-street-1933",
        "dictionaries": [
            432,
            502
        ],
        "location": null,
        "period": null,
        "serie": null,
        "genre": "genre painting",
        "material": null,
        "style": "Metaphysical art",
        "technique": null,
        "sizeX": 240.0,
        "sizeY": 195.0,
        "diameter": null,
        "auction": null,
        "yearOfTrade": null,
        "lastPrice": null,
        "galleryName": "Museum of Modern Art (MoMA), New York City, NY, US",
        "tags": "streets-and-squares",
        "description": null
    },
    {
        "title": "Guitar lesson",
        "contentId": 244705,
        "artistContentId": 244678,
        "artistName": "Balthus",
        "completitionYear": 1934,
        "yearAsString": "1934",
        "width": 520,
        "image": "https://uploads6.wikiart.org/images/balthus/guitar-lesson-1934.jpg!Large.jpg",
        "height": 600,
        "artistUrl": "balthus",
        "url": "guitar-lesson-1934",
        "dictionaries": [
            481,
            500
        ],
        "location": null,
        "period": null,
        "serie": null,
        "genre": "symbolic painting",
        "material": null,
        "style": "Surrealism",
        "technique": null,
        "sizeX": 138.4,
        "sizeY": 161.3,
        "diameter": null,
        "auction": null,
        "yearOfTrade": null,
        "lastPrice": null,
        "galleryName": "Private Collection",
        "tags": "allegories-and-symbols, female-nude, musical-instruments",
        "description": null
    },
    {
        "title": "Study to \"Guitar lesson\"",
        "contentId": 244778,
        "artistContentId": 244678,
        "artistName": "Balthus",
        "completitionYear": 1934,
        "yearAsString": "1934",
        "width": 800,
        "image": "https://uploads6.wikiart.org/images/balthus/study-to-guitar-lesson-1934.jpg!Large.jpg",
        "height": 504,
        "artistUrl": "balthus",
        "url": "study-to-guitar-lesson-1934",
        "dictionaries": [
            417,
            1192
        ],
        "location": null,
        "period": null,
        "serie": null,
        "genre": "sketch and study",
        "material": null,
        "style": "Expressionism",
        "technique": null,
        "sizeX": 40.0,
        "sizeY": 30.0,
        "diameter": null,
        "auction": null,
        "yearOfTrade": null,
        "lastPrice": null,
        "galleryName": null,
        "tags": "female-nude",
        "description": null
    },
    {
        "title": "Cathy",
        "contentId": 244684,
        "artistContentId": 244678,
        "artistName": "Balthus",
        "completitionYear": 1935,
        "yearAsString": "1935",
        "width": 515,
        "image": "https://uploads7.wikiart.org/images/balthus/cathy-1935.jpg!Large.jpg",
        "height": 635,
        "artistUrl": "balthus",
        "url": "cathy-1935",
        "dictionaries": [
            417,
            496
        ],
        "location": null,
        "period": null,
        "serie": null,
        "genre": "literary painting",
        "material": null,
        "style": "Expressionism",
        "technique": null,
        "sizeX": null,
        "sizeY": null,
        "diameter": null,
        "auction": null,
        "yearOfTrade": null,
        "lastPrice": null,
        "galleryName": null,
        "tags": null,
        "description": null
    },
    {
        "title": "Lady Abdy",
        "contentId": 244711,
        "artistContentId": 244678,
        "artistName": "Balthus",
        "completitionYear": 1935,
        "yearAsString": "1935",
        "width": 1385,
        "image": "https://uploads2.wikiart.org/images/balthus/lady-abdy-1935.jpg!Large.jpg",
        "height": 1915,
        "artistUrl": "balthus",
        "url": "lady-abdy-1935",
        "dictionaries": [
            417,
            502
        ],
        "location": null,
        "period": null,
        "serie": null,
        "genre": "genre painting",
        "material": null,
        "style": "Expressionism",
        "technique": null,
        "sizeX": null,
        "sizeY": null,
        "diameter": null,
        "auction": null,
        "yearOfTrade": null,
        "lastPrice": null,
        "galleryName": null,
        "tags": "characters-and-emotions",
        "description": null
    },
    {
        "title": "Study for the Dream I",
        "contentId": 244774,
        "artistContentId": 244678,
        "artistName": "Balthus",
        "completitionYear": 1935,
        "yearAsString": "1935",
        "width": 800,
        "image": "https://uploads5.wikiart.org/images/balthus/study-for-the-dream-i-1935.jpg!Large.jpg",
        "height": 662,
        "artistUrl": "balthus",
        "url": "study-for-the-dream-i-1935",
        "dictionaries": [
            417,
            1192
        ],
        "location": null,
        "period": null,
        "serie": null,
        "genre": "sketch and study",
        "material": null,
        "style": "Expressionism",
        "technique": null,
        "sizeX": null,
        "sizeY": null,
        "diameter": null,
        "auction": null,
        "yearOfTrade": null,
        "lastPrice": null,
        "galleryName": null,
        "tags": "leisure-and-sleep",
        "description": null
    },
    {
        "title": "The King of Cats",
        "contentId": 244795,
        "artistContentId": 244678,
        "artistName": "Balthus",
        "completitionYear": 1935,
        "yearAsString": "1935",
        "width": 1165,
        "image": "https://uploads0.wikiart.org/images/balthus/the-king-of-cats-1935.jpg!Large.jpg",
        "height": 1901,
        "artistUrl": "balthus",
        "url": "the-king-of-cats-1935",
        "dictionaries": [
            417,
            481,
            520
        ],
        "location": null,
        "period": null,
        "serie": null,
        "genre": "self-portrait",
        "material": null,
        "style": "Expressionism, Surrealism",
        "technique": null,
        "sizeX": 48.0,
        "sizeY": 71.0,
        "diameter": null,
        "auction": null,
        "yearOfTrade": null,
        "lastPrice": null,
        "galleryName": "Private Collection",
        "tags": "animals, male-portraits, famous-people, cats",
        "description": null
    },
    {
        "title": "Andre Derain",
        "contentId": 244681,
        "artistContentId": 244678,
        "artistName": "Balthus",
        "completitionYear": 1936,
        "yearAsString": "1936",
        "width": 1335,
        "image": "https://uploads5.wikiart.org/images/balthus/andre-derain-1936.jpg!Large.jpg",
        "height": 2043,
        "artistUrl": "balthus",
        "url": "andre-derain-1936",
        "dictionaries": [
            417,
            519
        ],
        "location": null,
        "period": null,
        "serie": null,
        "genre": "portrait",
        "material": null,
        "style": "Expressionism",
        "technique": null,
        "sizeX": null,
        "sizeY": null,
        "diameter": null,
        "auction": null,
        "yearOfTrade": null,
        "lastPrice": null,
        "galleryName": "Museum of Modern Art (MoMA), New York City, NY, US",
        "tags": "male-portraits, famous-people, studios-and-workshops",
        "description": null
    },
    {
        "title": "Children",
        "contentId": 244687,
        "artistContentId": 244678,
        "artistName": "Balthus",
        "completitionYear": 1937,
        "yearAsString": "1937",
        "width": 2185,
        "image": "https://uploads1.wikiart.org/images/balthus/children-1937.jpg!Large.jpg",
        "height": 2091,
        "artistUrl": "balthus",
        "url": "children-1937",
        "dictionaries": [
            481,
            502
        ],
        "location": null,
        "period": null,
        "serie": null,
        "genre": "genre painting",
        "material": null,
        "style": "Surrealism",
        "technique": null,
        "sizeX": null,
        "sizeY": null,
        "diameter": null,
        "auction": null,
        "yearOfTrade": null,
        "lastPrice": null,
        "galleryName": "Musée Picasso, Paris, France",
        "tags": "children",
        "description": null
    },
    {
        "title": "Girl and Cat",
        "contentId": 244697,
        "artistContentId": 244678,
        "artistName": "Balthus",
        "completitionYear": 1937,
        "yearAsString": "1937",
        "width": 1423,
        "image": "https://uploads5.wikiart.org/images/balthus/girl-and-cat-1937.jpg!Large.jpg",
        "height": 1620,
        "artistUrl": "balthus",
        "url": "girl-and-cat-1937",
        "dictionaries": [
            417,
            502
        ],
        "location": null,
        "period": null,
        "serie": null,
        "genre": "genre painting",
        "material": null,
        "style": "Expressionism",
        "technique": null,
        "sizeX": null,
        "sizeY": null,
        "diameter": null,
        "auction": null,
        "yearOfTrade": null,
        "lastPrice": null,
        "galleryName": "Private Collection",
        "tags": "animals, cats, leisure-and-sleep",
        "description": null
    },
    {
        "title": "Joan Miro and his daughter Dolores",
        "contentId": 244709,
        "artistContentId": 244678,
        "artistName": "Balthus",
        "completitionYear": 1937,
        "yearAsString": "1937",
        "width": 1385,
        "image": "https://uploads0.wikiart.org/images/balthus/joan-miro-and-his-daughter-dolores-1937.jpg!Large.jpg",
        "height": 2042,
        "artistUrl": "balthus",
        "url": "joan-miro-and-his-daughter-dolores-1937",
        "dictionaries": [
            417,
            519
        ],
        "location": null,
        "period": null,
        "serie": null,
        "genre": "portrait",
        "material": null,
        "style": "Expressionism",
        "technique": null,
        "sizeX": 88.9,
        "sizeY": 130.2,
        "diameter": null,
        "auction": null,
        "yearOfTrade": null,
        "lastPrice": null,
        "galleryName": "Museum of Modern Art (MoMA), New York City, NY, US",
        "tags": "famous-people, family-portraits",
        "description": null
    },
    {
        "title": "Still life",
        "contentId": 244769,
        "artistContentId": 244678,
        "artistName": "Balthus",
        "completitionYear": 1937,
        "yearAsString": "1937",
        "width": 1543,
        "image": "https://uploads3.wikiart.org/images/balthus/still-life-1937.jpg!Large.jpg",
        "height": 1249,
        "artistUrl": "balthus",
        "url": "still-life-1937",
        "dictionaries": [
            465,
            512
        ],
        "location": null,
        "period": null,
        "serie": null,
        "genre": "still life",
        "material": null,
        "style": "Realism",
        "technique": null,
        "sizeX": null,
        "sizeY": null,
        "diameter": null,
        "auction": null,
        "yearOfTrade": null,
        "lastPrice": null,
        "galleryName": null,
        "tags": "dishware-and-cutlery, food-and-beverages",
        "description": null
    },
    {
        "title": "The mountain",
        "contentId": 244798,
        "artistContentId": 244678,
        "artistName": "Balthus",
        "completitionYear": 1937,
        "yearAsString": "1937",
        "width": 2399,
        "image": "https://uploads5.wikiart.org/images/balthus/the-mountain-1937.jpg!Large.jpg",
        "height": 1633,
        "artistUrl": "balthus",
        "url": "the-mountain-1937",
        "dictionaries": [
            481,
            502
        ],
        "location": null,
        "period": null,
        "serie": null,
        "genre": "genre painting",
        "material": null,
        "style": "Surrealism",
        "technique": null,
        "sizeX": 365.8,
        "sizeY": 248.9,
        "diameter": null,
        "auction": null,
        "yearOfTrade": null,
        "lastPrice": null,
        "galleryName": null,
        "tags": "characters-and-emotions, mountains",
        "description": null
    },
    {
        "title": "The white skirt",
        "contentId": 244808,
        "artistContentId": 244678,
        "artistName": "Balthus",
        "completitionYear": 1937,
        "yearAsString": "1937",
        "width": 1965,
        "image": "https://uploads8.wikiart.org/images/balthus/the-white-skirt-1937.jpg!Large.jpg",
        "height": 1440,
        "artistUrl": "balthus",
        "url": "the-white-skirt-1937",
        "dictionaries": [
            417,
            519
        ],
        "location": null,
        "period": null,
        "serie": null,
        "genre": "portrait",
        "material": null,
        "style": "Expressionism",
        "technique": null,
        "sizeX": 162.0,
        "sizeY": 130.0,
        "diameter": null,
        "auction": null,
        "yearOfTrade": null,
        "lastPrice": null,
        "galleryName": "Private Collection",
        "tags": "leisure-and-sleep",
        "description": null
    },
    {
        "title": "The Victim",
        "contentId": 244806,
        "artistContentId": 244678,
        "artistName": "Balthus",
        "completitionYear": 1938,
        "yearAsString": "1938",
        "width": 1772,
        "image": "https://uploads7.wikiart.org/images/balthus/the-victim.jpg!Large.jpg",
        "height": 1019,
        "artistUrl": "balthus",
        "url": "the-victim",
        "dictionaries": [
            417,
            521
        ],
        "location": null,
        "period": null,
        "serie": null,
        "genre": "nude painting (nu)",
        "material": null,
        "style": "Expressionism",
        "technique": null,
        "sizeX": null,
        "sizeY": null,
        "diameter": null,
        "auction": null,
        "yearOfTrade": null,
        "lastPrice": null,
        "galleryName": null,
        "tags": "female-nude",
        "description": null
    },
    {
        "title": "Thérèse",
        "contentId": 244811,
        "artistContentId": 244678,
        "artistName": "Balthus",
        "completitionYear": 1938,
        "yearAsString": "1938",
        "width": 1307,
        "image": "https://uploads0.wikiart.org/images/balthus/thérèse-1938.jpg!Large.jpg",
        "height": 1623,
        "artistUrl": "balthus",
        "url": "thérèse-1938",
        "dictionaries": [
            417,
            519
        ],
        "location": null,
        "period": null,
        "serie": null,
        "genre": "portrait",
        "material": null,
        "style": "Expressionism",
        "technique": null,
        "sizeX": 81.3,
        "sizeY": 100.3,
        "diameter": null,
        "auction": null,
        "yearOfTrade": null,
        "lastPrice": null,
        "galleryName": null,
        "tags": "female-portraits, children portraits",
        "description": null
    },
    {
        "title": "Thérèse dreaming",
        "contentId": 244812,
        "artistContentId": 244678,
        "artistName": "Balthus",
        "completitionYear": 1938,
        "yearAsString": "1938",
        "width": 945,
        "image": "https://uploads0.wikiart.org/images/balthus/thérèse-dreaming-1938.jpg!Large.jpg",
        "height": 1076,
        "artistUrl": "balthus",
        "url": "thérèse-dreaming-1938",
        "dictionaries": [
            417,
            502
        ],
        "location": null,
        "period": null,
        "serie": null,
        "genre": "genre painting",
        "material": null,
        "style": "Expressionism",
        "technique": null,
        "sizeX": null,
        "sizeY": null,
        "diameter": null,
        "auction": null,
        "yearOfTrade": null,
        "lastPrice": null,
        "galleryName": null,
        "tags": "animals, cats, leisure-and-sleep",
        "description": null
    },
    {
        "title": "Larchant",
        "contentId": 244716,
        "artistContentId": 244678,
        "artistName": "Balthus",
        "completitionYear": 1939,
        "yearAsString": "1939",
        "width": 2185,
        "image": "https://uploads1.wikiart.org/images/balthus/larchant-1939.jpg!Large.jpg",
        "height": 1739,
        "artistUrl": "balthus",
        "url": "larchant-1939",
        "dictionaries": [
            417,
            481,
            504
        ],
        "location": null,
        "period": null,
        "serie": null,
        "genre": "landscape",
        "material": null,
        "style": "Expressionism, Surrealism",
        "technique": null,
        "sizeX": null,
        "sizeY": null,
        "diameter": null,
        "auction": null,
        "yearOfTrade": null,
        "lastPrice": null,
        "galleryName": null,
        "tags": "countryside, fields-and-plains",
        "description": null
    },
    {
        "title": "Self-portrait",
        "contentId": 244765,
        "artistContentId": 244678,
        "artistName": "Balthus",
        "completitionYear": 1940,
        "yearAsString": "1940",
        "width": 627,
        "image": "https://uploads6.wikiart.org/images/balthus/self-portrait-1940.jpg!Large.jpg",
        "height": 873,
        "artistUrl": "balthus",
        "url": "self-portrait-1940",
        "dictionaries": [
            417,
            520
        ],
        "location": null,
        "period": null,
        "serie": null,
        "genre": "self-portrait",
        "material": null,
        "style": "Expressionism",
        "technique": null,
        "sizeX": null,
        "sizeY": null,
        "diameter": null,
        "auction": null,
        "yearOfTrade": null,
        "lastPrice": null,
        "galleryName": null,
        "tags": "male-portraits, famous-people",
        "description": null
    },
    {
        "title": "The Cherry Tree",
        "contentId": 244788,
        "artistContentId": 244678,
        "artistName": "Balthus",
        "completitionYear": 1940,
        "yearAsString": "1940",
        "width": 1552,
        "image": "https://uploads3.wikiart.org/images/balthus/the-cherry-tree.jpg!Large.jpg",
        "height": 1999,
        "artistUrl": "balthus",
        "url": "the-cherry-tree",
        "dictionaries": [
            417,
            504
        ],
        "location": null,
        "period": null,
        "serie": null,
        "genre": "landscape",
        "material": null,
        "style": "Expressionism",
        "technique": null,
        "sizeX": 73.0,
        "sizeY": 93.0,
        "diameter": null,
        "auction": null,
        "yearOfTrade": null,
        "lastPrice": null,
        "galleryName": "Private Collection",
        "tags": "summer, children, gardens-and-parks",
        "description": null
    },
    {
        "title": "Girl on a white horse",
        "contentId": 244701,
        "artistContentId": 244678,
        "artistName": "Balthus",
        "completitionYear": 1941,
        "yearAsString": "1941",
        "width": 582,
        "image": "https://uploads5.wikiart.org/images/balthus/girl-on-a-white-horse-1941.jpg!Large.jpg",
        "height": 523,
        "artistUrl": "balthus",
        "url": "girl-on-a-white-horse-1941",
        "dictionaries": [
            417,
            502
        ],
        "location": null,
        "period": null,
        "serie": null,
        "genre": "genre painting",
        "material": null,
        "style": "Expressionism",
        "technique": null,
        "sizeX": null,
        "sizeY": null,
        "diameter": null,
        "auction": null,
        "yearOfTrade": null,
        "lastPrice": null,
        "galleryName": null,
        "tags": "allegories-and-symbols, children, female-nude, horsemen",
        "description": null
    },
    {
        "title": "Drawing room",
        "contentId": 244692,
        "artistContentId": 244678,
        "artistName": "Balthus",
        "completitionYear": 1942,
        "yearAsString": "1942",
        "width": 838,
        "image": "https://uploads5.wikiart.org/images/balthus/drawing-room-1942.jpg!Large.jpg",
        "height": 645,
        "artistUrl": "balthus",
        "url": "drawing-room-1942",
        "dictionaries": [
            417,
            502
        ],
        "location": null,
        "period": null,
        "serie": null,
        "genre": "genre painting",
        "material": null,
        "style": "Expressionism",
        "technique": null,
        "sizeX": 146.9,
        "sizeY": 114.8,
        "diameter": null,
        "auction": null,
        "yearOfTrade": null,
        "lastPrice": null,
        "galleryName": "Museum of Modern Art (MoMA), New York City, NY, US",
        "tags": "animals, children, cats, reading-and-writing, leisure-and-sleep",
        "description": null
    },
    {
        "title": "Landscape with Oxen",
        "contentId": 244715,
        "artistContentId": 244678,
        "artistName": "Balthus",
        "completitionYear": 1942,
        "yearAsString": "1942",
        "width": 2405,
        "image": "https://uploads3.wikiart.org/images/balthus/landscape-with-oxen-1942.jpg!Large.jpg",
        "height": 1720,
        "artistUrl": "balthus",
        "url": "landscape-with-oxen-1942",
        "dictionaries": [
            417,
            504
        ],
        "location": null,
        "period": null,
        "serie": null,
        "genre": "landscape",
        "material": null,
        "style": "Expressionism",
        "technique": null,
        "sizeX": 72.0,
        "sizeY": 100.0,
        "diameter": null,
        "auction": null,
        "yearOfTrade": null,
        "lastPrice": null,
        "galleryName": "Private Collection",
        "tags": "animals, countryside, mountains, oxen",
        "description": null
    },
    {
        "title": "Still Life with a Figure",
        "contentId": 244771,
        "artistContentId": 244678,
        "artistName": "Balthus",
        "completitionYear": 1942,
        "yearAsString": "1942",
        "width": 1511,
        "image": "https://uploads8.wikiart.org/images/balthus/still-life-with-a-figure-1942.jpg!Large.jpg",
        "height": 1192,
        "artistUrl": "balthus",
        "url": "still-life-with-a-figure-1942",
        "dictionaries": [
            417,
            502
        ],
        "location": null,
        "period": null,
        "serie": null,
        "genre": "genre painting",
        "material": null,
        "style": "Expressionism",
        "technique": null,
        "sizeX": 93.4,
        "sizeY": 74.4,
        "diameter": null,
        "auction": null,
        "yearOfTrade": null,
        "lastPrice": null,
        "galleryName": "Tate Modern, London, UK",
        "tags": "domestic-settings",
        "description": null
    },
    {
        "title": "Drawing Room",
        "contentId": 244693,
        "artistContentId": 244678,
        "artistName": "Balthus",
        "completitionYear": 1943,
        "yearAsString": "1943",
        "width": 2270,
        "image": "https://uploads0.wikiart.org/images/balthus/drawing-room.jpg!Large.jpg",
        "height": 1695,
        "artistUrl": "balthus",
        "url": "drawing-room",
        "dictionaries": [
            417,
            502
        ],
        "location": null,
        "period": null,
        "serie": null,
        "genre": "genre painting",
        "material": null,
        "style": "Expressionism",
        "technique": null,
        "sizeX": 146.7,
        "sizeY": 113.7,
        "diameter": null,
        "auction": null,
        "yearOfTrade": null,
        "lastPrice": null,
        "galleryName": null,
        "tags": "children, reading-and-writing, leisure-and-sleep",
        "description": null
    },
    {
        "title": "Gotteron",
        "contentId": 244702,
        "artistContentId": 244678,
        "artistName": "Balthus",
        "completitionYear": 1943,
        "yearAsString": "1943",
        "width": 1674,
        "image": "https://uploads1.wikiart.org/images/balthus/gotteron-1943.jpg!Large.jpg",
        "height": 1924,
        "artistUrl": "balthus",
        "url": "gotteron-1943",
        "dictionaries": [
            417,
            504
        ],
        "location": null,
        "period": null,
        "serie": null,
        "genre": "landscape",
        "material": null,
        "style": "Expressionism",
        "technique": null,
        "sizeX": 99.5,
        "sizeY": 115.0,
        "diameter": null,
        "auction": null,
        "yearOfTrade": null,
        "lastPrice": null,
        "galleryName": "Private Collection",
        "tags": "twilight-and-night, forests-and-trees, cliffs-and-rocks",
        "description": null
    },
    {
        "title": "Patience",
        "contentId": 244755,
        "artistContentId": 244678,
        "artistName": "Balthus",
        "completitionYear": 1943,
        "yearAsString": "1943",
        "width": 1423,
        "image": "https://uploads1.wikiart.org/images/balthus/patience-1943.jpg!Large.jpg",
        "height": 1397,
        "artistUrl": "balthus",
        "url": "patience-1943",
        "dictionaries": [
            417,
            502
        ],
        "location": null,
        "period": null,
        "serie": null,
        "genre": "genre painting",
        "material": null,
        "style": "Expressionism",
        "technique": null,
        "sizeX": null,
        "sizeY": null,
        "diameter": null,
        "auction": null,
        "yearOfTrade": null,
        "lastPrice": null,
        "galleryName": null,
        "tags": "characters-and-emotions",
        "description": null
    },
    {
        "title": "Sleeping Girl",
        "contentId": 244767,
        "artistContentId": 244678,
        "artistName": "Balthus",
        "completitionYear": 1943,
        "yearAsString": "1943",
        "width": 512,
        "image": "https://uploads6.wikiart.org/images/balthus/sleeping-girl-1943.jpg!Large.jpg",
        "height": 403,
        "artistUrl": "balthus",
        "url": "sleeping-girl-1943",
        "dictionaries": [
            417,
            502
        ],
        "location": null,
        "period": null,
        "serie": null,
        "genre": "genre painting",
        "material": null,
        "style": "Expressionism",
        "technique": null,
        "sizeX": null,
        "sizeY": null,
        "diameter": null,
        "auction": null,
        "yearOfTrade": null,
        "lastPrice": null,
        "galleryName": "Tate Modern, London, UK",
        "tags": "leisure-and-sleep",
        "description": null
    },
    {
        "title": "Princess Maria Volkonsky at the age of twelve",
        "contentId": 244758,
        "artistContentId": 244678,
        "artistName": "Balthus",
        "completitionYear": 1945,
        "yearAsString": "1945",
        "width": 1338,
        "image": "https://uploads2.wikiart.org/images/balthus/princess-maria-volkonsky-at-the-age-of-twelve-1945.jpg!Large.jpg",
        "height": 1725,
        "artistUrl": "balthus",
        "url": "princess-maria-volkonsky-at-the-age-of-twelve-1945",
        "dictionaries": [
            417,
            519
        ],
        "location": null,
        "period": null,
        "serie": null,
        "genre": "portrait",
        "material": null,
        "style": "Expressionism",
        "technique": null,
        "sizeX": 64.0,
        "sizeY": 82.0,
        "diameter": null,
        "auction": null,
        "yearOfTrade": null,
        "lastPrice": null,
        "galleryName": null,
        "tags": "female-portraits, children portraits",
        "description": null
    },
    {
        "title": "The Golden Years",
        "contentId": 244794,
        "artistContentId": 244678,
        "artistName": "Balthus",
        "completitionYear": 1945,
        "yearAsString": "1945",
        "width": 2346,
        "image": "https://uploads4.wikiart.org/images/balthus/the-golden-years.jpg!Large.jpg",
        "height": 1715,
        "artistUrl": "balthus",
        "url": "the-golden-years",
        "dictionaries": [
            417,
            502
        ],
        "location": null,
        "period": null,
        "serie": null,
        "genre": "genre painting",
        "material": null,
        "style": "Expressionism",
        "technique": null,
        "sizeX": 148.0,
        "sizeY": 199.0,
        "diameter": null,
        "auction": null,
        "yearOfTrade": null,
        "lastPrice": null,
        "galleryName": null,
        "tags": "fireplaces, leisure-and-sleep",
        "description": null
    },
    {
        "title": "The Room",
        "contentId": 244801,
        "artistContentId": 244678,
        "artistName": "Balthus",
        "completitionYear": 1948,
        "yearAsString": "1948",
        "width": 336,
        "image": "https://uploads1.wikiart.org/images/balthus/the-room-1948.jpg!Large.jpg",
        "height": 400,
        "artistUrl": "balthus",
        "url": "the-room-1948",
        "dictionaries": [
            417,
            521
        ],
        "location": null,
        "period": null,
        "serie": null,
        "genre": "nude painting (nu)",
        "material": null,
        "style": "Expressionism",
        "technique": null,
        "sizeX": null,
        "sizeY": null,
        "diameter": null,
        "auction": null,
        "yearOfTrade": null,
        "lastPrice": null,
        "galleryName": null,
        "tags": "female-nude",
        "description": null
    },
    {
        "title": "Nude with Cat",
        "contentId": 244751,
        "artistContentId": 244678,
        "artistName": "Balthus",
        "completitionYear": 1949,
        "yearAsString": "1949",
        "width": 1755,
        "image": "https://uploads6.wikiart.org/images/balthus/nude-with-cat-1949.jpg!Large.jpg",
        "height": 1352,
        "artistUrl": "balthus",
        "url": "nude-with-cat-1949",
        "dictionaries": [
            417,
            521
        ],
        "location": null,
        "period": null,
        "serie": null,
        "genre": "nude painting (nu)",
        "material": null,
        "style": "Expressionism",
        "technique": null,
        "sizeX": 65.1,
        "sizeY": 80.5,
        "diameter": null,
        "auction": null,
        "yearOfTrade": null,
        "lastPrice": null,
        "galleryName": "National Gallery of Victoria (NGV), Melbourne, Australia",
        "tags": "animals, cats, female-nude, leisure-and-sleep",
        "description": null
    },
    {
        "title": "The Mediterranean Cat",
        "contentId": 244796,
        "artistContentId": 244678,
        "artistName": "Balthus",
        "completitionYear": 1949,
        "yearAsString": "1949",
        "width": 2169,
        "image": "https://uploads5.wikiart.org/images/balthus/the-mediterranean-cat-1949.jpg!Large.jpg",
        "height": 1453,
        "artistUrl": "balthus",
        "url": "the-mediterranean-cat-1949",
        "dictionaries": [
            481,
            500
        ],
        "location": null,
        "period": null,
        "serie": null,
        "genre": "symbolic painting",
        "material": null,
        "style": "Surrealism",
        "technique": null,
        "sizeX": null,
        "sizeY": null,
        "diameter": null,
        "auction": null,
        "yearOfTrade": null,
        "lastPrice": null,
        "galleryName": "Private Collection",
        "tags": "animals, children, cats, mealtimes, boats-and-ships, rainbows",
        "description": null
    },
    {
        "title": "The week with four thursdays",
        "contentId": 244807,
        "artistContentId": 244678,
        "artistName": "Balthus",
        "completitionYear": 1949,
        "yearAsString": "1949",
        "width": 3386,
        "image": "https://uploads1.wikiart.org/00104/images/balthus/1994-9-1.jpg!Large.jpg",
        "height": 3895,
        "artistUrl": "balthus",
        "url": "the-week-with-four-thursdays-1949",
        "dictionaries": [
            417,
            502
        ],
        "location": null,
        "period": null,
        "serie": null,
        "genre": "genre painting",
        "material": null,
        "style": "Expressionism",
        "technique": null,
        "sizeX": null,
        "sizeY": null,
        "diameter": null,
        "auction": null,
        "yearOfTrade": null,
        "lastPrice": null,
        "galleryName": null,
        "tags": "leisure-and-sleep",
        "description": null
    },
    {
        "title": "Girl on a Bed",
        "contentId": 244700,
        "artistContentId": 244678,
        "artistName": "Balthus",
        "completitionYear": 1950,
        "yearAsString": "1950",
        "width": 374,
        "image": "https://uploads1.wikiart.org/images/balthus/girl-on-a-bed.jpg!Large.jpg",
        "height": 312,
        "artistUrl": "balthus",
        "url": "girl-on-a-bed",
        "dictionaries": [
            417,
            521
        ],
        "location": null,
        "period": null,
        "serie": null,
        "genre": "nude painting (nu)",
        "material": null,
        "style": "Expressionism",
        "technique": null,
        "sizeX": 55.2,
        "sizeY": 45.7,
        "diameter": null,
        "auction": null,
        "yearOfTrade": null,
        "lastPrice": null,
        "galleryName": "Philadelphia Museum of Art, Philadelphia, PA, US",
        "tags": "animals, cats, female-nude, leisure-and-sleep",
        "description": null
    },
    {
        "title": "The cardgame",
        "contentId": 244783,
        "artistContentId": 244678,
        "artistName": "Balthus",
        "completitionYear": 1950,
        "yearAsString": "1950",
        "width": 1772,
        "image": "https://uploads5.wikiart.org/images/balthus/the-cardgame-1950.jpg!Large.jpg",
        "height": 1287,
        "artistUrl": "balthus",
        "url": "the-cardgame-1950",
        "dictionaries": [
            417,
            502
        ],
        "location": null,
        "period": null,
        "serie": null,
        "genre": "genre painting",
        "material": null,
        "style": "Expressionism",
        "technique": null,
        "sizeX": null,
        "sizeY": null,
        "diameter": null,
        "auction": null,
        "yearOfTrade": null,
        "lastPrice": null,
        "galleryName": "Thyssen-Bornemisza Museum, Madrid, Spain",
        "tags": "games-and-sport",
        "description": null
    },
    {
        "title": "Nude with her arms raised",
        "contentId": 244752,
        "artistContentId": 244678,
        "artistName": "Balthus",
        "completitionYear": 1951,
        "yearAsString": "1951",
        "width": 313,
        "image": "https://uploads0.wikiart.org/images/balthus/nude-with-her-arms-raised-1951.jpg!Large.jpg",
        "height": 600,
        "artistUrl": "balthus",
        "url": "nude-with-her-arms-raised-1951",
        "dictionaries": [
            417,
            521
        ],
        "location": null,
        "period": null,
        "serie": null,
        "genre": "nude painting (nu)",
        "material": null,
        "style": "Expressionism",
        "technique": null,
        "sizeX": null,
        "sizeY": null,
        "diameter": null,
        "auction": null,
        "yearOfTrade": null,
        "lastPrice": null,
        "galleryName": null,
        "tags": "female-nude",
        "description": null
    },
    {
        "title": "Window, Cour de Rohan",
        "contentId": 244816,
        "artistContentId": 244678,
        "artistName": "Balthus",
        "completitionYear": 1951,
        "yearAsString": "1951",
        "width": 963,
        "image": "https://uploads4.wikiart.org/images/balthus/window-cour-de-rohan-1951.jpg!Large.jpg",
        "height": 1884,
        "artistUrl": "balthus",
        "url": "window-cour-de-rohan-1951",
        "dictionaries": [
            432,
            509
        ],
        "location": null,
        "period": null,
        "serie": null,
        "genre": "cityscape",
        "material": null,
        "style": "Metaphysical art",
        "technique": null,
        "sizeX": null,
        "sizeY": null,
        "diameter": null,
        "auction": null,
        "yearOfTrade": null,
        "lastPrice": null,
        "galleryName": "Georges Pompidou Center, Paris, France",
        "tags": "houses-and-buildings, doors-and-windows",
        "description": null
    },
    {
        "title": "The Room",
        "contentId": 244800,
        "artistContentId": 244678,
        "artistName": "Balthus",
        "completitionYear": 1953,
        "yearAsString": "1953",
        "width": 2440,
        "image": "https://uploads5.wikiart.org/images/balthus/the-room.jpg!Large.jpg",
        "height": 1986,
        "artistUrl": "balthus",
        "url": "the-room",
        "dictionaries": [
            417,
            521
        ],
        "location": null,
        "period": null,
        "serie": null,
        "genre": "nude painting (nu)",
        "material": null,
        "style": "Expressionism",
        "technique": null,
        "sizeX": 270.5,
        "sizeY": 335.0,
        "diameter": null,
        "auction": null,
        "yearOfTrade": null,
        "lastPrice": null,
        "galleryName": "Private Collection",
        "tags": "female-nude",
        "description": null
    },
    {
        "title": "Colette sitting",
        "contentId": 244688,
        "artistContentId": 244678,
        "artistName": "Balthus",
        "completitionYear": 1954,
        "yearAsString": "1954",
        "width": 634,
        "image": "https://uploads3.wikiart.org/images/balthus/colette-sitting.jpg!Large.jpg",
        "height": 800,
        "artistUrl": "balthus",
        "url": "colette-sitting",
        "dictionaries": [
            417,
            519
        ],
        "location": null,
        "period": null,
        "serie": null,
        "genre": "portrait",
        "material": null,
        "style": "Expressionism",
        "technique": null,
        "sizeX": null,
        "sizeY": null,
        "diameter": null,
        "auction": null,
        "yearOfTrade": null,
        "lastPrice": null,
        "galleryName": null,
        "tags": "female-portraits, children portraits",
        "description": null
    },
    {
        "title": "The passage of Commerce Saint-Andre",
        "contentId": 244799,
        "artistContentId": 244678,
        "artistName": "Balthus",
        "completitionYear": 1954,
        "yearAsString": "1954",
        "width": 1430,
        "image": "https://uploads1.wikiart.org/images/balthus/the-passage-of-commerce-saint-andre-1954.jpg!Large.jpg",
        "height": 1556,
        "artistUrl": "balthus",
        "url": "the-passage-of-commerce-saint-andre-1954",
        "dictionaries": [
            432,
            502
        ],
        "location": null,
        "period": null,
        "serie": null,
        "genre": "genre painting",
        "material": null,
        "style": "Metaphysical art",
        "technique": null,
        "sizeX": 330.0,
        "sizeY": 294.0,
        "diameter": null,
        "auction": null,
        "yearOfTrade": null,
        "lastPrice": null,
        "galleryName": "Private Collection",
        "tags": "streets-and-squares",
        "description": null
    },
    {
        "title": "Three sisters",
        "contentId": 244814,
        "artistContentId": 244678,
        "artistName": "Balthus",
        "completitionYear": 1954,
        "yearAsString": "1954",
        "width": 1782,
        "image": "https://uploads6.wikiart.org/images/balthus/three-sisters-1954.jpg!Large.jpg",
        "height": 892,
        "artistUrl": "balthus",
        "url": "three-sisters-1954",
        "dictionaries": [
            417,
            502
        ],
        "location": null,
        "period": null,
        "serie": null,
        "genre": "genre painting",
        "material": null,
        "style": "Expressionism",
        "technique": null,
        "sizeX": 120.0,
        "sizeY": 60.0,
        "diameter": null,
        "auction": null,
        "yearOfTrade": null,
        "lastPrice": null,
        "galleryName": "Private Collection",
        "tags": "leisure-and-sleep",
        "description": null
    },
    {
        "title": "Chassy by the fireplace at workshop",
        "contentId": 244686,
        "artistContentId": 244678,
        "artistName": "Balthus",
        "completitionYear": 1955,
        "yearAsString": "1955",
        "width": 800,
        "image": "https://uploads5.wikiart.org/images/balthus/chassy-by-the-fireplace-at-workshop.jpg!Large.jpg",
        "height": 631,
        "artistUrl": "balthus",
        "url": "chassy-by-the-fireplace-at-workshop",
        "dictionaries": [
            417,
            502
        ],
        "location": null,
        "period": null,
        "serie": null,
        "genre": "genre painting",
        "material": null,
        "style": "Expressionism",
        "technique": null,
        "sizeX": null,
        "sizeY": null,
        "diameter": null,
        "auction": null,
        "yearOfTrade": null,
        "lastPrice": null,
        "galleryName": null,
        "tags": "studios-and-workshops, leisure-and-sleep",
        "description": null
    },
    {
        "title": "Figure in Front of a Mantel",
        "contentId": 244694,
        "artistContentId": 244678,
        "artistName": "Balthus",
        "completitionYear": 1955,
        "yearAsString": "1955",
        "width": 2050,
        "image": "https://uploads2.wikiart.org/images/balthus/figure-in-front-of-a-mantel-1955.jpg!Large.jpg",
        "height": 2189,
        "artistUrl": "balthus",
        "url": "figure-in-front-of-a-mantel-1955",
        "dictionaries": [
            417,
            481,
            502
        ],
        "location": null,
        "period": null,
        "serie": null,
        "genre": "genre painting",
        "material": null,
        "style": "Expressionism, Surrealism",
        "technique": null,
        "sizeX": 64.5,
        "sizeY": 75.0,
        "diameter": null,
        "auction": null,
        "yearOfTrade": null,
        "lastPrice": null,
        "galleryName": null,
        "tags": "female-nude, women-and-mirrors",
        "description": null
    },
    {
        "title": "Getting Up",
        "contentId": 244695,
        "artistContentId": 244678,
        "artistName": "Balthus",
        "completitionYear": 1955,
        "yearAsString": "1955",
        "width": 642,
        "image": "https://uploads3.wikiart.org/images/balthus/getting-up-1955.jpg!Large.jpg",
        "height": 800,
        "artistUrl": "balthus",
        "url": "getting-up-1955",
        "dictionaries": [
            417,
            521
        ],
        "location": null,
        "period": null,
        "serie": null,
        "genre": "nude painting (nu)",
        "material": null,
        "style": "Expressionism",
        "technique": null,
        "sizeX": 161.0,
        "sizeY": 130.4,
        "diameter": null,
        "auction": null,
        "yearOfTrade": null,
        "lastPrice": null,
        "galleryName": "Scottish National Gallery of Modern Art, Edinburgh, UK",
        "tags": "female-nude",
        "description": null
    },
    {
        "title": "Girl at the window",
        "contentId": 244698,
        "artistContentId": 244678,
        "artistName": "Balthus",
        "completitionYear": 1955,
        "yearAsString": "1955",
        "width": 1437,
        "image": "https://uploads2.wikiart.org/images/balthus/girl-at-the-window-1955.jpg!Large.jpg",
        "height": 2199,
        "artistUrl": "balthus",
        "url": "girl-at-the-window-1955",
        "dictionaries": [
            417,
            502
        ],
        "location": null,
        "period": null,
        "serie": null,
        "genre": "genre painting",
        "material": null,
        "style": "Expressionism",
        "technique": null,
        "sizeX": 130.5,
        "sizeY": 196.0,
        "diameter": null,
        "auction": null,
        "yearOfTrade": null,
        "lastPrice": null,
        "galleryName": "Private Collection",
        "tags": "doors-and-windows, lonely figures",
        "description": null
    },
    {
        "title": "Great landscape with trees (The triangular field)",
        "contentId": 244704,
        "artistContentId": 244678,
        "artistName": "Balthus",
        "completitionYear": 1955,
        "yearAsString": "1955",
        "width": 2340,
        "image": "https://uploads4.wikiart.org/images/balthus/great-landscape-with-trees-the-triangular-field-1955.jpg!Large.jpg",
        "height": 1630,
        "artistUrl": "balthus",
        "url": "great-landscape-with-trees-the-triangular-field-1955",
        "dictionaries": [
            417,
            504
        ],
        "location": null,
        "period": null,
        "serie": null,
        "genre": "landscape",
        "material": null,
        "style": "Expressionism",
        "technique": null,
        "sizeX": null,
        "sizeY": null,
        "diameter": null,
        "auction": null,
        "yearOfTrade": null,
        "lastPrice": null,
        "galleryName": null,
        "tags": "fields-and-plains",
        "description": null
    },
    {
        "title": "Landscape in Morvan",
        "contentId": 244714,
        "artistContentId": 244678,
        "artistName": "Balthus",
        "completitionYear": 1955,
        "yearAsString": "1955",
        "width": 800,
        "image": "https://uploads3.wikiart.org/images/balthus/landscape-in-morvan-1955.jpg!Large.jpg",
        "height": 609,
        "artistUrl": "balthus",
        "url": "landscape-in-morvan-1955",
        "dictionaries": [
            417,
            504
        ],
        "location": null,
        "period": null,
        "serie": null,
        "genre": "landscape",
        "material": null,
        "style": "Expressionism",
        "technique": null,
        "sizeX": 35.0,
        "sizeY": 27.0,
        "diameter": null,
        "auction": null,
        "yearOfTrade": null,
        "lastPrice": null,
        "galleryName": null,
        "tags": "forests-and-trees, cliffs-and-rocks",
        "description": null
    },
    {
        "title": "Patience",
        "contentId": 244756,
        "artistContentId": 244678,
        "artistName": "Balthus",
        "completitionYear": 1955,
        "yearAsString": "1955",
        "width": 798,
        "image": "https://uploads1.wikiart.org/images/balthus/patience-1955.jpg!Large.jpg",
        "height": 800,
        "artistUrl": "balthus",
        "url": "patience-1955",
        "dictionaries": [
            417,
            502
        ],
        "location": null,
        "period": null,
        "serie": null,
        "genre": "genre painting",
        "material": null,
        "style": "Expressionism",
        "technique": null,
        "sizeX": null,
        "sizeY": null,
        "diameter": null,
        "auction": null,
        "yearOfTrade": null,
        "lastPrice": null,
        "galleryName": "Private Collection",
        "tags": "animals, cats, characters-and-emotions",
        "description": null
    },
    {
        "title": "The Dream",
        "contentId": 244790,
        "artistContentId": 244678,
        "artistName": "Balthus",
        "completitionYear": 1955,
        "yearAsString": "1955",
        "width": 2193,
        "image": "https://uploads6.wikiart.org/images/balthus/the-dream.jpg!Large.jpg",
        "height": 1769,
        "artistUrl": "balthus",
        "url": "the-dream",
        "dictionaries": [
            417,
            502
        ],
        "location": null,
        "period": null,
        "serie": null,
        "genre": "genre painting",
        "material": null,
        "style": "Expressionism",
        "technique": null,
        "sizeX": 130.0,
        "sizeY": 162.0,
        "diameter": null,
        "auction": null,
        "yearOfTrade": null,
        "lastPrice": null,
        "galleryName": "Private Collection",
        "tags": "leisure-and-sleep",
        "description": null
    },
    {
        "title": "Young girl with white skirt",
        "contentId": 244819,
        "artistContentId": 244678,
        "artistName": "Balthus",
        "completitionYear": 1955,
        "yearAsString": "1955",
        "width": 1680,
        "image": "https://uploads2.wikiart.org/images/balthus/young-girl-with-white-skirt-1955.jpg!Large.jpg",
        "height": 2240,
        "artistUrl": "balthus",
        "url": "young-girl-with-white-skirt-1955",
        "dictionaries": [
            417,
            521
        ],
        "location": null,
        "period": null,
        "serie": null,
        "genre": "nude painting (nu)",
        "material": null,
        "style": "Expressionism",
        "technique": null,
        "sizeX": null,
        "sizeY": null,
        "diameter": null,
        "auction": null,
        "yearOfTrade": null,
        "lastPrice": null,
        "galleryName": "Private Collection",
        "tags": "female-portraits",
        "description": null
    },
    {
        "title": "Still Life (quince and pear)",
        "contentId": 244770,
        "artistContentId": 244678,
        "artistName": "Balthus",
        "completitionYear": 1956,
        "yearAsString": "1956",
        "width": 800,
        "image": "https://uploads1.wikiart.org/images/balthus/still-life-quince-and-pear-1956.jpg!Large.jpg",
        "height": 530,
        "artistUrl": "balthus",
        "url": "still-life-quince-and-pear-1956",
        "dictionaries": [
            417,
            512
        ],
        "location": null,
        "period": null,
        "serie": null,
        "genre": "still life",
        "material": null,
        "style": "Expressionism",
        "technique": null,
        "sizeX": null,
        "sizeY": null,
        "diameter": null,
        "auction": null,
        "yearOfTrade": null,
        "lastPrice": null,
        "galleryName": null,
        "tags": "fruits-and-vegetables",
        "description": null
    },
    {
        "title": "The Golden Fruit",
        "contentId": 244793,
        "artistContentId": 244678,
        "artistName": "Balthus",
        "completitionYear": 1956,
        "yearAsString": "1956",
        "width": 1395,
        "image": "https://uploads0.wikiart.org/images/balthus/the-golden-fruit-1956.jpg!Large.jpg",
        "height": 1416,
        "artistUrl": "balthus",
        "url": "the-golden-fruit-1956",
        "dictionaries": [
            417,
            502
        ],
        "location": null,
        "period": null,
        "serie": null,
        "genre": "genre painting",
        "material": null,
        "style": "Expressionism",
        "technique": null,
        "sizeX": 159.0,
        "sizeY": 160.5,
        "diameter": null,
        "auction": null,
        "yearOfTrade": null,
        "lastPrice": null,
        "galleryName": "Private Collection",
        "tags": "allegories-and-symbols",
        "description": null
    },
    {
        "title": "Landscape in Chassy",
        "contentId": 244712,
        "artistContentId": 244678,
        "artistName": "Balthus",
        "completitionYear": 1957,
        "yearAsString": "1957",
        "width": 800,
        "image": "https://uploads7.wikiart.org/images/balthus/landscape-in-chassy.jpg!Large.jpg",
        "height": 665,
        "artistUrl": "balthus",
        "url": "landscape-in-chassy",
        "dictionaries": [
            417,
            504
        ],
        "location": null,
        "period": null,
        "serie": null,
        "genre": "landscape",
        "material": null,
        "style": "Expressionism",
        "technique": null,
        "sizeX": null,
        "sizeY": null,
        "diameter": null,
        "auction": null,
        "yearOfTrade": null,
        "lastPrice": null,
        "galleryName": null,
        "tags": "fields-and-plains",
        "description": null
    },
    {
        "title": "Large Landscape with a Tree",
        "contentId": 244717,
        "artistContentId": 244678,
        "artistName": "Balthus",
        "completitionYear": 1957,
        "yearAsString": "1957",
        "width": 2335,
        "image": "https://uploads2.wikiart.org/images/balthus/large-landscape-with-a-tree-1957.jpg!Large.jpg",
        "height": 1871,
        "artistUrl": "balthus",
        "url": "large-landscape-with-a-tree-1957",
        "dictionaries": [
            417,
            504
        ],
        "location": null,
        "period": null,
        "serie": null,
        "genre": "landscape",
        "material": null,
        "style": "Expressionism",
        "technique": null,
        "sizeX": 162.0,
        "sizeY": 130.5,
        "diameter": null,
        "auction": null,
        "yearOfTrade": null,
        "lastPrice": null,
        "galleryName": "Georges Pompidou Center, Paris, France",
        "tags": "countryside, cottages-and-farmhouses",
        "description": null
    },
    {
        "title": "The Toilet",
        "contentId": 244804,
        "artistContentId": 244678,
        "artistName": "Balthus",
        "completitionYear": 1957,
        "yearAsString": "1957",
        "width": 1718,
        "image": "https://uploads3.wikiart.org/images/balthus/the-toilet-1957.jpg!Large.jpg",
        "height": 2193,
        "artistUrl": "balthus",
        "url": "the-toilet-1957",
        "dictionaries": [
            417,
            521
        ],
        "location": null,
        "period": null,
        "serie": null,
        "genre": "nude painting (nu)",
        "material": null,
        "style": "Expressionism",
        "technique": null,
        "sizeX": 162.0,
        "sizeY": 130.8,
        "diameter": null,
        "auction": null,
        "yearOfTrade": null,
        "lastPrice": null,
        "galleryName": "Private Collection",
        "tags": "female-nude",
        "description": null
    },
    {
        "title": "The Yonne Valley",
        "contentId": 244809,
        "artistContentId": 244678,
        "artistName": "Balthus",
        "completitionYear": 1957,
        "yearAsString": "1957",
        "width": 800,
        "image": "https://uploads0.wikiart.org/images/balthus/the-yonne-valley-1957.jpg!Large.jpg",
        "height": 498,
        "artistUrl": "balthus",
        "url": "the-yonne-valley-1957",
        "dictionaries": [
            417,
            504
        ],
        "location": null,
        "period": null,
        "serie": null,
        "genre": "landscape",
        "material": null,
        "style": "Expressionism",
        "technique": null,
        "sizeX": null,
        "sizeY": null,
        "diameter": null,
        "auction": null,
        "yearOfTrade": null,
        "lastPrice": null,
        "galleryName": null,
        "tags": "countryside, cottages-and-farmhouses",
        "description": null
    },
    {
        "title": "Young Girl at the Window",
        "contentId": 244818,
        "artistContentId": 244678,
        "artistName": "Balthus",
        "completitionYear": 1957,
        "yearAsString": "1957",
        "width": 2176,
        "image": "https://uploads8.wikiart.org/images/balthus/young-girl-at-the-window-1957.jpg!Large.jpg",
        "height": 2152,
        "artistUrl": "balthus",
        "url": "young-girl-at-the-window-1957",
        "dictionaries": [
            417,
            502
        ],
        "location": null,
        "period": null,
        "serie": null,
        "genre": "genre painting",
        "material": null,
        "style": "Expressionism",
        "technique": null,
        "sizeX": null,
        "sizeY": null,
        "diameter": null,
        "auction": null,
        "yearOfTrade": null,
        "lastPrice": null,
        "galleryName": null,
        "tags": "doors-and-windows, leisure-and-sleep",
        "description": null
    },
    {
        "title": "Big Landscape with Cow",
        "contentId": 244682,
        "artistContentId": 244678,
        "artistName": "Balthus",
        "completitionYear": 1958,
        "yearAsString": "1958",
        "width": 1863,
        "image": "https://uploads1.wikiart.org/images/balthus/big-landscape-with-cow.jpg!Large.jpg",
        "height": 2256,
        "artistUrl": "balthus",
        "url": "big-landscape-with-cow",
        "dictionaries": [
            417,
            504
        ],
        "location": null,
        "period": null,
        "serie": null,
        "genre": "landscape",
        "material": null,
        "style": "Expressionism",
        "technique": null,
        "sizeX": null,
        "sizeY": null,
        "diameter": null,
        "auction": null,
        "yearOfTrade": null,
        "lastPrice": null,
        "galleryName": null,
        "tags": "animals, countryside, cottages-and-farmhouses, cows",
        "description": null
    },
    {
        "title": "Portrait of Baroness Alain de Rothschild",
        "contentId": 244757,
        "artistContentId": 244678,
        "artistName": "Balthus",
        "completitionYear": 1958,
        "yearAsString": "1958",
        "width": 618,
        "image": "https://uploads6.wikiart.org/images/balthus/portrait-of-baroness-alain-de-rothschild-1958.jpg!Large.jpg",
        "height": 800,
        "artistUrl": "balthus",
        "url": "portrait-of-baroness-alain-de-rothschild-1958",
        "dictionaries": [
            417,
            519
        ],
        "location": null,
        "period": null,
        "serie": null,
        "genre": "portrait",
        "material": null,
        "style": "Expressionism",
        "technique": null,
        "sizeX": null,
        "sizeY": null,
        "diameter": null,
        "auction": null,
        "yearOfTrade": null,
        "lastPrice": null,
        "galleryName": null,
        "tags": "female-portraits",
        "description": null
    },
    {
        "title": "Still Life with Lamp",
        "contentId": 244772,
        "artistContentId": 244678,
        "artistName": "Balthus",
        "completitionYear": 1958,
        "yearAsString": "1958",
        "width": 2084,
        "image": "https://uploads4.wikiart.org/images/balthus/still-life-with-lamp-1958.jpg!Large.jpg",
        "height": 1599,
        "artistUrl": "balthus",
        "url": "still-life-with-lamp-1958",
        "dictionaries": [
            417,
            512
        ],
        "location": null,
        "period": null,
        "serie": null,
        "genre": "still life",
        "material": null,
        "style": "Expressionism",
        "technique": null,
        "sizeX": null,
        "sizeY": null,
        "diameter": null,
        "auction": null,
        "yearOfTrade": null,
        "lastPrice": null,
        "galleryName": null,
        "tags": "fruits-and-vegetables",
        "description": null
    },
    {
        "title": "Still Life with Lamp",
        "contentId": 244773,
        "artistContentId": 244678,
        "artistName": "Balthus",
        "completitionYear": 1958,
        "yearAsString": "1958",
        "width": 629,
        "image": "https://uploads6.wikiart.org/images/balthus/still-life-with-lamp-1958-1.jpg!Large.jpg",
        "height": 800,
        "artistUrl": "balthus",
        "url": "still-life-with-lamp-1958-1",
        "dictionaries": [
            417,
            512
        ],
        "location": null,
        "period": null,
        "serie": null,
        "genre": "still life",
        "material": null,
        "style": "Expressionism",
        "technique": null,
        "sizeX": 130.0,
        "sizeY": 162.0,
        "diameter": null,
        "auction": null,
        "yearOfTrade": null,
        "lastPrice": null,
        "galleryName": null,
        "tags": "lamps-and-candles, dishware-and-cutlery",
        "description": null
    },
    {
        "title": "Study for the siesta",
        "contentId": 244776,
        "artistContentId": 244678,
        "artistName": "Balthus",
        "completitionYear": 1958,
        "yearAsString": "1958",
        "width": 706,
        "image": "https://uploads4.wikiart.org/images/balthus/study-for-the-siesta-1958.jpg!Large.jpg",
        "height": 800,
        "artistUrl": "balthus",
        "url": "study-for-the-siesta-1958",
        "dictionaries": [
            417,
            1192
        ],
        "location": null,
        "period": null,
        "serie": null,
        "genre": "sketch and study",
        "material": null,
        "style": "Expressionism",
        "technique": null,
        "sizeX": null,
        "sizeY": null,
        "diameter": null,
        "auction": null,
        "yearOfTrade": null,
        "lastPrice": null,
        "galleryName": null,
        "tags": "flowers-and-plants",
        "description": null
    },
    {
        "title": "The bouquet of roses on the window",
        "contentId": 244782,
        "artistContentId": 244678,
        "artistName": "Balthus",
        "completitionYear": 1958,
        "yearAsString": "1958",
        "width": 1945,
        "image": "https://uploads0.wikiart.org/images/balthus/the-bouquet-of-roses-on-the-window-1958.jpg!Large.jpg",
        "height": 2036,
        "artistUrl": "balthus",
        "url": "the-bouquet-of-roses-on-the-window-1958",
        "dictionaries": [
            417,
            504
        ],
        "location": null,
        "period": null,
        "serie": null,
        "genre": "landscape",
        "material": null,
        "style": "Expressionism",
        "technique": null,
        "sizeX": null,
        "sizeY": null,
        "diameter": null,
        "auction": null,
        "yearOfTrade": null,
        "lastPrice": null,
        "galleryName": null,
        "tags": "flowers-and-plants, doors-and-windows",
        "description": null
    },
    {
        "title": "The Child with Pigeons",
        "contentId": 244789,
        "artistContentId": 244678,
        "artistName": "Balthus",
        "completitionYear": 1959,
        "yearAsString": "1959",
        "width": 1765,
        "image": "https://uploads1.wikiart.org/images/balthus/the-child-with-pigeons.jpg!Large.jpg",
        "height": 2216,
        "artistUrl": "balthus",
        "url": "the-child-with-pigeons",
        "dictionaries": [
            417,
            502
        ],
        "location": null,
        "period": null,
        "serie": null,
        "genre": "genre painting",
        "material": null,
        "style": "Expressionism",
        "technique": null,
        "sizeX": 130.8,
        "sizeY": 162.0,
        "diameter": null,
        "auction": null,
        "yearOfTrade": null,
        "lastPrice": null,
        "galleryName": null,
        "tags": "children",
        "description": null
    },
    {
        "title": "Pastoral",
        "contentId": 244754,
        "artistContentId": 244678,
        "artistName": "Balthus",
        "completitionYear": 1960,
        "yearAsString": "1960",
        "width": 800,
        "image": "https://uploads1.wikiart.org/images/balthus/pastoral-1960.jpg!Large.jpg",
        "height": 392,
        "artistUrl": "balthus",
        "url": "pastoral-1960",
        "dictionaries": [
            417,
            504
        ],
        "location": null,
        "period": null,
        "serie": null,
        "genre": "landscape",
        "material": null,
        "style": "Expressionism",
        "technique": null,
        "sizeX": 50.0,
        "sizeY": 100.0,
        "diameter": null,
        "auction": null,
        "yearOfTrade": null,
        "lastPrice": null,
        "galleryName": null,
        "tags": "countryside, fields-and-plains",
        "description": null
    },
    {
        "title": "The Moth",
        "contentId": 244797,
        "artistContentId": 244678,
        "artistName": "Balthus",
        "completitionYear": 1960,
        "yearAsString": "1960",
        "width": 1766,
        "image": "https://uploads1.wikiart.org/images/balthus/the-moth-1960.jpg!Large.jpg",
        "height": 2226,
        "artistUrl": "balthus",
        "url": "the-moth-1960",
        "dictionaries": [
            417,
            502
        ],
        "location": null,
        "period": null,
        "serie": null,
        "genre": "genre painting",
        "material": null,
        "style": "Expressionism",
        "technique": null,
        "sizeX": 130.0,
        "sizeY": 162.0,
        "diameter": null,
        "auction": null,
        "yearOfTrade": null,
        "lastPrice": null,
        "galleryName": "Georges Pompidou Center, Paris, France",
        "tags": "lamps-and-candles, dreams-and-hallucinations, night",
        "description": null
    },
    {
        "title": "The Turkish Room",
        "contentId": 244805,
        "artistContentId": 244678,
        "artistName": "Balthus",
        "completitionYear": 1963,
        "yearAsString": "1963",
        "width": 2328,
        "image": "https://uploads0.wikiart.org/images/balthus/the-turkish-room-1963.jpg!Large.jpg",
        "height": 2039,
        "artistUrl": "balthus",
        "url": "the-turkish-room-1963",
        "dictionaries": [
            417,
            521
        ],
        "location": null,
        "period": null,
        "serie": null,
        "genre": "nude painting (nu)",
        "material": null,
        "style": "Expressionism",
        "technique": null,
        "sizeX": null,
        "sizeY": null,
        "diameter": null,
        "auction": null,
        "yearOfTrade": null,
        "lastPrice": null,
        "galleryName": "Georges Pompidou Center, Paris, France",
        "tags": "women-and-mirrors, leisure-and-sleep",
        "description": null
    },
    {
        "title": "Three sisters",
        "contentId": 244815,
        "artistContentId": 244678,
        "artistName": "Balthus",
        "completitionYear": 1964,
        "yearAsString": "1964",
        "width": 1941,
        "image": "https://uploads6.wikiart.org/images/balthus/three-sisters-1964.jpg!Large.jpg",
        "height": 1297,
        "artistUrl": "balthus",
        "url": "three-sisters-1964",
        "dictionaries": [
            417,
            502
        ],
        "location": null,
        "period": null,
        "serie": null,
        "genre": "genre painting",
        "material": null,
        "style": "Expressionism",
        "technique": null,
        "sizeX": 192.0,
        "sizeY": 130.0,
        "diameter": null,
        "auction": null,
        "yearOfTrade": null,
        "lastPrice": null,
        "galleryName": "Private Collection",
        "tags": "leisure-and-sleep",
        "description": null
    },
    {
        "title": "Bust of the young girl",
        "contentId": 244683,
        "artistContentId": 244678,
        "artistName": "Balthus",
        "completitionYear": 1965,
        "yearAsString": "1965",
        "width": 546,
        "image": "https://uploads1.wikiart.org/images/balthus/bust-of-the-young-girl.jpg!Large.jpg",
        "height": 800,
        "artistUrl": "balthus",
        "url": "bust-of-the-young-girl",
        "dictionaries": [
            417,
            1192
        ],
        "location": null,
        "period": null,
        "serie": null,
        "genre": "sketch and study",
        "material": null,
        "style": "Expressionism",
        "technique": null,
        "sizeX": 70.0,
        "sizeY": 100.0,
        "diameter": null,
        "auction": null,
        "yearOfTrade": null,
        "lastPrice": null,
        "galleryName": null,
        "tags": "female-portraits",
        "description": null
    },
    {
        "title": "Three sisters",
        "contentId": 244813,
        "artistContentId": 244678,
        "artistName": "Balthus",
        "completitionYear": 1965,
        "yearAsString": "1965",
        "width": 1864,
        "image": "https://uploads1.wikiart.org/images/balthus/three-sisters.jpg!Large.jpg",
        "height": 1355,
        "artistUrl": "balthus",
        "url": "three-sisters",
        "dictionaries": [
            417,
            502
        ],
        "location": null,
        "period": null,
        "serie": null,
        "genre": "genre painting",
        "material": null,
        "style": "Expressionism",
        "technique": null,
        "sizeX": 127.0,
        "sizeY": 170.0,
        "diameter": null,
        "auction": null,
        "yearOfTrade": null,
        "lastPrice": null,
        "galleryName": "Private Collection",
        "tags": "animals, cats, leisure-and-sleep",
        "description": null
    },
    {
        "title": "Japanese Girl with a Black Mirror",
        "contentId": 244707,
        "artistContentId": 244678,
        "artistName": "Balthus",
        "completitionYear": 1967,
        "yearAsString": "1967",
        "width": 2189,
        "image": "https://uploads8.wikiart.org/images/balthus/japanese-girl-with-a-black-mirror-1967.jpg!Large.jpg",
        "height": 1664,
        "artistUrl": "balthus",
        "url": "japanese-girl-with-a-black-mirror-1967",
        "dictionaries": [
            417,
            426,
            502
        ],
        "location": null,
        "period": null,
        "serie": null,
        "genre": "genre painting",
        "material": null,
        "style": "Expressionism, Japonism",
        "technique": null,
        "sizeX": null,
        "sizeY": null,
        "diameter": null,
        "auction": null,
        "yearOfTrade": null,
        "lastPrice": null,
        "galleryName": null,
        "tags": "female-nude, women-and-mirrors",
        "description": null
    },
    {
        "title": "Japanese Girl with by the Red Table",
        "contentId": 244708,
        "artistContentId": 244678,
        "artistName": "Balthus",
        "completitionYear": 1967,
        "yearAsString": "1967",
        "width": 2199,
        "image": "https://uploads1.wikiart.org/images/balthus/japanese-girl-with-by-the-red-table-1967.jpg!Large.jpg",
        "height": 1643,
        "artistUrl": "balthus",
        "url": "japanese-girl-with-by-the-red-table-1967",
        "dictionaries": [
            417,
            426,
            502
        ],
        "location": null,
        "period": null,
        "serie": null,
        "genre": "genre painting",
        "material": null,
        "style": "Expressionism, Japonism",
        "technique": null,
        "sizeX": null,
        "sizeY": null,
        "diameter": null,
        "auction": null,
        "yearOfTrade": null,
        "lastPrice": null,
        "galleryName": null,
        "tags": "female-nude, leisure-and-sleep",
        "description": null
    },
    {
        "title": "Study for the painting \"Nude Resting\"",
        "contentId": 244775,
        "artistContentId": 244678,
        "artistName": "Balthus",
        "completitionYear": 1972,
        "yearAsString": "1972",
        "width": 1629,
        "image": "https://uploads1.wikiart.org/images/balthus/study-for-the-painting-nude-resting-1972.jpg!Large.jpg",
        "height": 2378,
        "artistUrl": "balthus",
        "url": "study-for-the-painting-nude-resting-1972",
        "dictionaries": [
            417,
            1192
        ],
        "location": null,
        "period": null,
        "serie": null,
        "genre": "sketch and study",
        "material": null,
        "style": "Expressionism",
        "technique": null,
        "sizeX": 71.1,
        "sizeY": 101.6,
        "diameter": null,
        "auction": null,
        "yearOfTrade": null,
        "lastPrice": null,
        "galleryName": null,
        "tags": "female-nude, leisure-and-sleep",
        "description": null
    },
    {
        "title": "The cardgame",
        "contentId": 244784,
        "artistContentId": 244678,
        "artistName": "Balthus",
        "completitionYear": 1973,
        "yearAsString": "1973",
        "width": 2362,
        "image": "https://uploads5.wikiart.org/images/balthus/the-cardgame-1973.jpg!Large.jpg",
        "height": 1999,
        "artistUrl": "balthus",
        "url": "the-cardgame-1973",
        "dictionaries": [
            417,
            502
        ],
        "location": null,
        "period": null,
        "serie": null,
        "genre": "genre painting",
        "material": null,
        "style": "Expressionism",
        "technique": null,
        "sizeX": 225.0,
        "sizeY": 190.0,
        "diameter": null,
        "auction": null,
        "yearOfTrade": null,
        "lastPrice": null,
        "galleryName": "Museum Boijmans van Beuningen, Rotterdam, Netherlands",
        "tags": "games-and-sport",
        "description": null
    },
    {
        "title": "Katia reading",
        "contentId": 244710,
        "artistContentId": 244678,
        "artistName": "Balthus",
        "completitionYear": 1974,
        "yearAsString": "1974",
        "width": 2334,
        "image": "https://uploads6.wikiart.org/images/balthus/katia-reading-1974.jpg!Large.jpg",
        "height": 2033,
        "artistUrl": "balthus",
        "url": "katia-reading-1974",
        "dictionaries": [
            417,
            502
        ],
        "location": null,
        "period": null,
        "serie": null,
        "genre": "genre painting",
        "material": null,
        "style": "Expressionism",
        "technique": null,
        "sizeX": 210.0,
        "sizeY": 180.0,
        "diameter": null,
        "auction": null,
        "yearOfTrade": null,
        "lastPrice": null,
        "galleryName": "Private Collection",
        "tags": "reading-and-writing",
        "description": null
    },
    {
        "title": "Nude in Profile",
        "contentId": 244748,
        "artistContentId": 244678,
        "artistName": "Balthus",
        "completitionYear": 1975,
        "yearAsString": "1975",
        "width": 2020,
        "image": "https://uploads3.wikiart.org/images/balthus/nude-in-profile.jpg!Large.jpg",
        "height": 2226,
        "artistUrl": "balthus",
        "url": "nude-in-profile",
        "dictionaries": [
            417,
            521
        ],
        "location": null,
        "period": null,
        "serie": null,
        "genre": "nude painting (nu)",
        "material": null,
        "style": "Expressionism",
        "technique": null,
        "sizeX": null,
        "sizeY": null,
        "diameter": null,
        "auction": null,
        "yearOfTrade": null,
        "lastPrice": null,
        "galleryName": null,
        "tags": "female-nude",
        "description": null
    },
    {
        "title": "Getting Up",
        "contentId": 244696,
        "artistContentId": 244678,
        "artistName": "Balthus",
        "completitionYear": 1977,
        "yearAsString": "1977",
        "width": 2104,
        "image": "https://uploads7.wikiart.org/images/balthus/getting-up.jpg!Large.jpg",
        "height": 2192,
        "artistUrl": "balthus",
        "url": "getting-up",
        "dictionaries": [
            417,
            521
        ],
        "location": null,
        "period": null,
        "serie": null,
        "genre": "nude painting (nu)",
        "material": null,
        "style": "Expressionism",
        "technique": null,
        "sizeX": 169.0,
        "sizeY": 159.5,
        "diameter": null,
        "auction": null,
        "yearOfTrade": null,
        "lastPrice": null,
        "galleryName": "Private Collection",
        "tags": "animals, cats, female-nude, leisure-and-sleep",
        "description": null
    },
    {
        "title": "Nude at Rest",
        "contentId": 244747,
        "artistContentId": 244678,
        "artistName": "Balthus",
        "completitionYear": 1977,
        "yearAsString": "1977",
        "width": 1718,
        "image": "https://uploads5.wikiart.org/images/balthus/nude-at-rest-1977.jpg!Large.jpg",
        "height": 2338,
        "artistUrl": "balthus",
        "url": "nude-at-rest-1977",
        "dictionaries": [
            417,
            521
        ],
        "location": null,
        "period": null,
        "serie": null,
        "genre": "nude painting (nu)",
        "material": null,
        "style": "Expressionism",
        "technique": null,
        "sizeX": 200.0,
        "sizeY": 150.0,
        "diameter": null,
        "auction": null,
        "yearOfTrade": null,
        "lastPrice": null,
        "galleryName": "Private Collection",
        "tags": "female-nude, leisure-and-sleep",
        "description": null
    },
    {
        "title": "The Cat in the Mirror",
        "contentId": 244785,
        "artistContentId": 244678,
        "artistName": "Balthus",
        "completitionYear": 1978,
        "yearAsString": "1978",
        "width": 1762,
        "image": "https://uploads0.wikiart.org/images/balthus/the-cat-in-the-mirror.jpg!Large.jpg",
        "height": 1860,
        "artistUrl": "balthus",
        "url": "the-cat-in-the-mirror",
        "dictionaries": [
            417,
            521
        ],
        "location": null,
        "period": null,
        "serie": null,
        "genre": "nude painting (nu)",
        "material": null,
        "style": "Expressionism",
        "technique": null,
        "sizeX": 180.0,
        "sizeY": 170.0,
        "diameter": null,
        "auction": null,
        "yearOfTrade": null,
        "lastPrice": null,
        "galleryName": "Private Collection",
        "tags": "animals, cats, female-nude, leisure-and-sleep",
        "description": null
    },
    {
        "title": "Montecalvello",
        "contentId": 244720,
        "artistContentId": 244678,
        "artistName": "Balthus",
        "completitionYear": 1979,
        "yearAsString": "1979",
        "width": 1602,
        "image": "https://uploads6.wikiart.org/images/balthus/montecalvello-1979.jpg!Large.jpg",
        "height": 1309,
        "artistUrl": "balthus",
        "url": "montecalvello-1979",
        "dictionaries": [
            417,
            504
        ],
        "location": null,
        "period": null,
        "serie": null,
        "genre": "landscape",
        "material": null,
        "style": "Expressionism",
        "technique": null,
        "sizeX": null,
        "sizeY": null,
        "diameter": null,
        "auction": null,
        "yearOfTrade": null,
        "lastPrice": null,
        "galleryName": null,
        "tags": "mountains",
        "description": null
    },
    {
        "title": "Sleeping Nude",
        "contentId": 244768,
        "artistContentId": 244678,
        "artistName": "Balthus",
        "completitionYear": 1980,
        "yearAsString": "1980",
        "width": 1474,
        "image": "https://uploads6.wikiart.org/images/balthus/sleeping-nude-1980.jpg!Large.jpg",
        "height": 1978,
        "artistUrl": "balthus",
        "url": "sleeping-nude-1980",
        "dictionaries": [
            417,
            521
        ],
        "location": null,
        "period": null,
        "serie": null,
        "genre": "nude painting (nu)",
        "material": null,
        "style": "Expressionism",
        "technique": null,
        "sizeX": null,
        "sizeY": null,
        "diameter": null,
        "auction": null,
        "yearOfTrade": null,
        "lastPrice": null,
        "galleryName": null,
        "tags": "female-nude, leisure-and-sleep",
        "description": null
    },
    {
        "title": "Painter and his Model",
        "contentId": 244753,
        "artistContentId": 244678,
        "artistName": "Balthus",
        "completitionYear": 1981,
        "yearAsString": "1981",
        "width": 1558,
        "image": "https://uploads5.wikiart.org/images/balthus/painter-and-his-model-1981.jpg!Large.jpg",
        "height": 1531,
        "artistUrl": "balthus",
        "url": "painter-and-his-model-1981",
        "dictionaries": [
            417,
            502
        ],
        "location": null,
        "period": null,
        "serie": null,
        "genre": "genre painting",
        "material": null,
        "style": "Expressionism",
        "technique": null,
        "sizeX": 230.5,
        "sizeY": 226.5,
        "diameter": null,
        "auction": null,
        "yearOfTrade": null,
        "lastPrice": null,
        "galleryName": "Georges Pompidou Center, Paris, France",
        "tags": "arts-and-crafts, studios-and-workshops",
        "description": null
    },
    {
        "title": "Nude with a Silk Scarf",
        "contentId": 244750,
        "artistContentId": 244678,
        "artistName": "Balthus",
        "completitionYear": 1982,
        "yearAsString": "1982",
        "width": 650,
        "image": "https://uploads1.wikiart.org/images/balthus/nude-with-a-silk-scarf.jpg!Large.jpg",
        "height": 895,
        "artistUrl": "balthus",
        "url": "nude-with-a-silk-scarf",
        "dictionaries": [
            417,
            521
        ],
        "location": null,
        "period": null,
        "serie": null,
        "genre": "nude painting (nu)",
        "material": null,
        "style": "Expressionism",
        "technique": null,
        "sizeX": null,
        "sizeY": null,
        "diameter": null,
        "auction": null,
        "yearOfTrade": null,
        "lastPrice": null,
        "galleryName": null,
        "tags": "female-nude",
        "description": null
    },
    {
        "title": "Great composition with corbel",
        "contentId": 244703,
        "artistContentId": 244678,
        "artistName": "Balthus",
        "completitionYear": 1985,
        "yearAsString": "1985",
        "width": 1708,
        "image": "https://uploads8.wikiart.org/images/balthus/great-composition-with-corbel.jpg!Large.jpg",
        "height": 2341,
        "artistUrl": "balthus",
        "url": "great-composition-with-corbel",
        "dictionaries": [
            481,
            521
        ],
        "location": null,
        "period": null,
        "serie": null,
        "genre": "nude painting (nu)",
        "material": null,
        "style": "Surrealism",
        "technique": null,
        "sizeX": null,
        "sizeY": null,
        "diameter": null,
        "auction": null,
        "yearOfTrade": null,
        "lastPrice": null,
        "galleryName": null,
        "tags": "female-nude, leisure-and-sleep",
        "description": null
    },
    {
        "title": "Nude with a Guitar",
        "contentId": 244749,
        "artistContentId": 244678,
        "artistName": "Balthus",
        "completitionYear": 1986,
        "yearAsString": "1986",
        "width": 1586,
        "image": "https://uploads2.wikiart.org/images/balthus/nude-with-a-guitar-1986.jpg!Large.jpg",
        "height": 1965,
        "artistUrl": "balthus",
        "url": "nude-with-a-guitar-1986",
        "dictionaries": [
            417,
            521
        ],
        "location": null,
        "period": null,
        "serie": null,
        "genre": "nude painting (nu)",
        "material": null,
        "style": "Expressionism",
        "technique": null,
        "sizeX": null,
        "sizeY": null,
        "diameter": null,
        "auction": null,
        "yearOfTrade": null,
        "lastPrice": null,
        "galleryName": null,
        "tags": "female-nude, leisure-and-sleep",
        "description": null
    },
    {
        "title": "The Cat in the Mirror",
        "contentId": 244786,
        "artistContentId": 244678,
        "artistName": "Balthus",
        "completitionYear": 1988,
        "yearAsString": "1988",
        "width": 1562,
        "image": "https://uploads2.wikiart.org/images/balthus/the-cat-in-the-mirror-1.jpg!Large.jpg",
        "height": 1857,
        "artistUrl": "balthus",
        "url": "the-cat-in-the-mirror-1",
        "dictionaries": [
            417,
            502
        ],
        "location": null,
        "period": null,
        "serie": null,
        "genre": "genre painting",
        "material": null,
        "style": "Expressionism",
        "technique": null,
        "sizeX": 200.0,
        "sizeY": 170.0,
        "diameter": null,
        "auction": null,
        "yearOfTrade": null,
        "lastPrice": null,
        "galleryName": "Private Collection",
        "tags": "animals, cats, leisure-and-sleep",
        "description": null
    },
    {
        "title": "The Cat in the Mirror",
        "contentId": 244787,
        "artistContentId": 244678,
        "artistName": "Balthus",
        "completitionYear": 1990,
        "yearAsString": "1990",
        "width": 760,
        "image": "https://uploads2.wikiart.org/images/balthus/the-cat-in-the-mirror-2.jpg!Large.jpg",
        "height": 719,
        "artistUrl": "balthus",
        "url": "the-cat-in-the-mirror-2",
        "dictionaries": [
            417,
            502
        ],
        "location": null,
        "period": null,
        "serie": null,
        "genre": "genre painting",
        "material": null,
        "style": "Expressionism",
        "technique": null,
        "sizeX": 220.0,
        "sizeY": 195.0,
        "diameter": null,
        "auction": null,
        "yearOfTrade": null,
        "lastPrice": null,
        "galleryName": "Private Collection",
        "tags": "animals, cats, leisure-and-sleep",
        "description": null
    },
    {
        "title": "Young girl asleep",
        "contentId": 244817,
        "artistContentId": 244678,
        "artistName": "Balthus",
        "completitionYear": 1994,
        "yearAsString": "1994",
        "width": 1735,
        "image": "https://uploads1.wikiart.org/images/balthus/young-girl-asleep-1994.jpg!Large.jpg",
        "height": 2325,
        "artistUrl": "balthus",
        "url": "young-girl-asleep-1994",
        "dictionaries": [
            417,
            1192
        ],
        "location": null,
        "period": null,
        "serie": null,
        "genre": "sketch and study",
        "material": null,
        "style": "Expressionism",
        "technique": null,
        "sizeX": null,
        "sizeY": null,
        "diameter": null,
        "auction": null,
        "yearOfTrade": null,
        "lastPrice": null,
        "galleryName": null,
        "tags": "leisure-and-sleep",
        "description": null
    },
    {
        "title": "Girl kneeling, her arms on a chair",
        "contentId": 244699,
        "artistContentId": 244678,
        "artistName": "Balthus",
        "completitionYear": null,
        "yearAsString": "",
        "width": 2359,
        "image": "https://uploads3.wikiart.org/images/balthus/girl-kneeling-her-arms-on-a-chair.jpg!Large.jpg",
        "height": 1600,
        "artistUrl": "balthus",
        "url": "girl-kneeling-her-arms-on-a-chair",
        "dictionaries": [
            417,
            1192
        ],
        "location": null,
        "period": null,
        "serie": null,
        "genre": "sketch and study",
        "material": null,
        "style": "Expressionism",
        "technique": null,
        "sizeX": null,
        "sizeY": null,
        "diameter": null,
        "auction": null,
        "yearOfTrade": null,
        "lastPrice": null,
        "galleryName": null,
        "tags": "leisure-and-sleep",
        "description": null
    },
    {
        "title": "Landscape in Chassy",
        "contentId": 244713,
        "artistContentId": 244678,
        "artistName": "Balthus",
        "completitionYear": null,
        "yearAsString": "",
        "width": 638,
        "image": "https://uploads0.wikiart.org/images/balthus/landscape-in-chassy-1.jpg!Large.jpg",
        "height": 800,
        "artistUrl": "balthus",
        "url": "landscape-in-chassy-1",
        "dictionaries": [
            417,
            504
        ],
        "location": null,
        "period": null,
        "serie": null,
        "genre": "landscape",
        "material": null,
        "style": "Expressionism",
        "technique": null,
        "sizeX": null,
        "sizeY": null,
        "diameter": null,
        "auction": null,
        "yearOfTrade": null,
        "lastPrice": null,
        "galleryName": null,
        "tags": "countryside, ruins-and-columns",
        "description": null
    },
    {
        "title": "Study of a girl with a window",
        "contentId": 244777,
        "artistContentId": 244678,
        "artistName": "Balthus",
        "completitionYear": null,
        "yearAsString": "",
        "width": 800,
        "image": "https://uploads8.wikiart.org/images/balthus/study-of-a-girl-with-a-window.jpg!Large.jpg",
        "height": 624,
        "artistUrl": "balthus",
        "url": "study-of-a-girl-with-a-window",
        "dictionaries": [
            417,
            1192
        ],
        "location": null,
        "period": null,
        "serie": null,
        "genre": "sketch and study",
        "material": null,
        "style": "Expressionism",
        "technique": null,
        "sizeX": null,
        "sizeY": null,
        "diameter": null,
        "auction": null,
        "yearOfTrade": null,
        "lastPrice": null,
        "galleryName": null,
        "tags": "doors-and-windows, yards, lonely figures",
        "description": null
    }
]