[
    {
        "title": "Red Cap",
        "contentId": 325098,
        "artistContentId": 325097,
        "artistName": "Kuchera John C.",
        "completitionYear": 2010,
        "yearAsString": "2010",
        "width": 308,
        "image": "https://uploads2.wikiart.org/images/john-c-kuchera/red-cap.jpg!Large.jpg",
        "height": 400,
        "artistUrl": "john-c-kuchera",
        "url": "red-cap",
        "dictionaries": [],
        "location": "United States",
        "period": null,
        "serie": null,
        "genre": null,
        "material": null,
        "style": null,
        "technique": null,
        "sizeX": null,
        "sizeY": null,
        "diameter": null,
        "auction": null,
        "yearOfTrade": null,
        "lastPrice": null,
        "galleryName": null,
        "tags": null,
        "description": "John C. Kuchera spend the Summer of 2010 in Pittsford, NY taking care of his mom who was going through cancer.\r\nJohn's dad who is also a painter encouraged him to paint. "
    },
    {
        "title": "Mom",
        "contentId": 325099,
        "artistContentId": 325097,
        "artistName": "Kuchera John C.",
        "completitionYear": 2011,
        "yearAsString": "2011",
        "width": 1842,
        "image": "https://uploads3.wikiart.org/images/john-c-kuchera/mom-2011.jpg!Large.jpg",
        "height": 3300,
        "artistUrl": "john-c-kuchera",
        "url": "mom-2011",
        "dictionaries": [],
        "location": null,
        "period": null,
        "serie": null,
        "genre": null,
        "material": null,
        "style": null,
        "technique": null,
        "sizeX": null,
        "sizeY": null,
        "diameter": null,
        "auction": null,
        "yearOfTrade": null,
        "lastPrice": null,
        "galleryName": null,
        "tags": null,
        "description": null
    },
    {
        "title": "I Say Dance",
        "contentId": 325100,
        "artistContentId": 325097,
        "artistName": "Kuchera John C.",
        "completitionYear": 2012,
        "yearAsString": "2012",
        "width": 500,
        "image": "https://uploads2.wikiart.org/images/john-c-kuchera/i-say-dance-2012.jpg!Large.jpg",
        "height": 331,
        "artistUrl": "john-c-kuchera",
        "url": "i-say-dance-2012",
        "dictionaries": [],
        "location": null,
        "period": null,
        "serie": null,
        "genre": null,
        "material": null,
        "style": null,
        "technique": null,
        "sizeX": null,
        "sizeY": null,
        "diameter": null,
        "auction": null,
        "yearOfTrade": null,
        "lastPrice": null,
        "galleryName": null,
        "tags": null,
        "description": null
    },
    {
        "title": "In Guns we Trust",
        "contentId": 325101,
        "artistContentId": 325097,
        "artistName": "Kuchera John C.",
        "completitionYear": 2012,
        "yearAsString": "2012",
        "width": 500,
        "image": "https://uploads7.wikiart.org/images/john-c-kuchera/in-guns-we-trust-2012.jpg!Large.jpg",
        "height": 408,
        "artistUrl": "john-c-kuchera",
        "url": "in-guns-we-trust-2012",
        "dictionaries": [],
        "location": null,
        "period": null,
        "serie": null,
        "genre": null,
        "material": null,
        "style": null,
        "technique": null,
        "sizeX": null,
        "sizeY": null,
        "diameter": null,
        "auction": null,
        "yearOfTrade": null,
        "lastPrice": null,
        "galleryName": null,
        "tags": null,
        "description": null
    },
    {
        "title": "Lady in Blue",
        "contentId": 325102,
        "artistContentId": 325097,
        "artistName": "Kuchera John C.",
        "completitionYear": 2012,
        "yearAsString": "2012",
        "width": 500,
        "image": "https://uploads3.wikiart.org/images/john-c-kuchera/lady-in-blue-2012.jpg!Large.jpg",
        "height": 354,
        "artistUrl": "john-c-kuchera",
        "url": "lady-in-blue-2012",
        "dictionaries": [],
        "location": null,
        "period": null,
        "serie": null,
        "genre": null,
        "material": null,
        "style": null,
        "technique": null,
        "sizeX": null,
        "sizeY": null,
        "diameter": null,
        "auction": null,
        "yearOfTrade": null,
        "lastPrice": null,
        "galleryName": null,
        "tags": null,
        "description": null
    },
    {
        "title": "Time to Dance",
        "contentId": 325103,
        "artistContentId": 325097,
        "artistName": "Kuchera John C.",
        "completitionYear": 2012,
        "yearAsString": "2012",
        "width": 500,
        "image": "https://uploads4.wikiart.org/images/john-c-kuchera/time-to-dance-2012.jpg!Large.jpg",
        "height": 396,
        "artistUrl": "john-c-kuchera",
        "url": "time-to-dance-2012",
        "dictionaries": [],
        "location": null,
        "period": null,
        "serie": null,
        "genre": null,
        "material": null,
        "style": null,
        "technique": null,
        "sizeX": null,
        "sizeY": null,
        "diameter": null,
        "auction": null,
        "yearOfTrade": null,
        "lastPrice": null,
        "galleryName": null,
        "tags": null,
        "description": null
    }
]